{ 
    "jeu" : "Labyrinthe",
    "cooperative" : true, 
    "duration" : 300, 
    "hauteur" : 10,
    "largeur" : 10,
    "visibility" : 5,
    "%density" : 100,
    "seed" : 0,
    "use_seed" : true,
    "pv" : 20,
    "nb_obstacles" : 10,
    "nb_ennemis" : 4,
    "entities": [
      { "name" : "Apple",
        "automate": "Apple",
        "%densite": 0
      },
      { "name" : "Arc", 
        "automate": "Arc"
      },
      { "name" : "Bombe", 
        "automate": "Bombe",
        "%densite" : 0
      },
      { "name" : "Cassable", 
        "automate": "Cassable",
        "%densite" : 0
      },
      { "name" : "Epee", 
        "automate": "Epee"
      },
      { "name" : "Fleche", 
        "automate": "Fleche"
      },
      { "name" : "Interrupteur", 
        "automate": "Interrupteur",
        "pickable": false 
      },
      { "name" : "Invisible", 
        "automate": "Invisible",
        "%densite" : 100
      },
      { "name" : "Joueur1", 
        "automate": "Player1" 
      },
      { "name" : "Joueur2", 
        "automate": "Player2"
      },
      { "name" : "Lave", 
        "automate": "Lave"
      },
      { "name" : "Mine", 
        "automate": "Mine",
        "%densite": 0
      },
      { "name" : "Normal", 
        "automate": "Normal"
      },
      { "name" : "Pioche", 
        "automate": "Pioche",
        "%densite" : 0
      },
      { "name" : "Porte", 
        "automate": "Porte"
      },
      { "name" : "Potion", 
        "automate": "Potion",
        "%densite" : 0
      },
      { "name" : "Sable", 
        "automate": "Sable"
      },
      { "name" : "Selection", 
        "automate": "Selection"
      },
      { "name" : "Squelette", 
        "automate": "Squelette"
      },
      { "name" : "Teleporteur", 
        "automate": "Teleporteur"
      },
      { "name" : "Void", 
        "automate": "Void"
      },
      { "name" : "Zombie", 
        "automate": "Zombie"
      }
    ]
  }
